[{"sha":"dc6a74ed8a4478aa3cde2d8478ecfaa062e66c3e","author":"anarchysaiko","email":"gcccc@tuta.io","date":"2024-11-24 20:43:37","codeAdditionsCount":213,"codeDeletionsCount":1,"codeChangesCount":214},{"sha":"16b61bf4831dd46e21b56475a0b7b21d26a8f435","author":"anarchysaiko","email":"gcccc@tuta.io","date":"2024-11-20 13:40:17","codeAdditionsCount":89,"codeDeletionsCount":1,"codeChangesCount":90},{"sha":"d6bb324fd1e42b829887cf6cbb6637f97360b2d7","author":"anarchysaiko","email":"gcccc@tuta.io","date":"2024-11-19 17:10:33","codeAdditionsCount":9,"codeDeletionsCount":0,"codeChangesCount":9},{"sha":"5bdd393829e0d60f5993261a449ac4db05b63f8b","author":"anarchysaiko","email":"gcccc@tuta.io","date":"2024-11-18 20:24:03","codeAdditionsCount":77,"codeDeletionsCount":1,"codeChangesCount":78},{"sha":"1fda8636309e9cd0d8ef7e4ffb935c68f7fa8de4","author":"anarchysaiko","email":"gcccc@tuta.io","date":"2024-11-13 14:07:47","codeAdditionsCount":136,"codeDeletionsCount":8,"codeChangesCount":144},{"sha":"334f9d8751299e0be0b03b488a7fe700c7fc158a","author":"anarchysaiko","email":"gcccc@tuta.io","date":"2024-11-12 20:15:56","codeAdditionsCount":13,"codeDeletionsCount":14,"codeChangesCount":27},{"sha":"96c66e03a9958a020fc9216986add6b87496e715","author":"anarchysaiko","email":"gcccc@tuta.io","date":"2024-11-12 19:48:51","codeAdditionsCount":0,"codeDeletionsCount":75,"codeChangesCount":75},{"sha":"a44c746acfb5fe8c587aab270fb67139baae7e68","author":"anarchysaiko","email":"gcccc@tuta.io","date":"2024-11-12 19:42:22","codeAdditionsCount":125,"codeDeletionsCount":0,"codeChangesCount":125}]