{
  "repo_name": "get-job",
  "monthly_stars": {
    "2025-1": 1,
    "2025-2": 3,
    "2025-3": 0,
    "2025-4": 0,
    "2025-5": 0,
    "2025-6": 1,
    "2025-7": 0,
    "2025-8": 0,
    "2025-9": 0,
    "2025-10": 0,
    "2025-11": 1,
    "2025-12": 1,
    "2026-1": 1,
    "2026-2": 0,
    "2026-3": 0,
    "2026-4": 0
  },
  "monthly_total_stars": {
    "2025-1": 1,
    "2025-2": 4,
    "2025-3": 4,
    "2025-4": 4,
    "2025-5": 4,
    "2025-6": 5,
    "2025-7": 5,
    "2025-8": 5,
    "2025-9": 5,
    "2025-10": 5,
    "2025-11": 6,
    "2025-12": 7,
    "2026-1": 8,
    "2026-2": 8,
    "2026-3": 8,
    "2026-4": 8
  },
  "star_count": 8
}